{
  "type": "Feature",
  "properties": {
    "gn:gn_country":"FM",
    "gn:gn_fcode":"PPL",
    "gn:gn_pop":427,
    "gn:population":427,
    "iso:country":"FM",
    "qs_pg:aaroncc":"FM",
    "qs_pg:gn_country":"FM",
    "qs_pg:gn_fcode":"PPL",
    "qs_pg:gn_pop":427,
    "qs_pg:name":"Piis Village",
    "qs_pg:photos_9r":0,
    "qs_pg:photos_sr":0,
    "qs_pg:pop_sr":2,
    "qs_pg:qs_pg_placetype":"locality",
    "wof:name":"Piis Village",
    "wof:placetype":"locality",
    "wof:population":427
},
  "geometry": {"coordinates":[152.70226,6.83636],"type":"Point"}
}