{
  "type": "Feature",
  "properties": {
    "gn:country":"FM",
    "gn:fcode":"ADM2",
    "gn:population":927,
    "iso:country":"FM",
    "label:eng_x_preferred_longname":[
        "Lekinioch Municipality"
    ],
    "label:eng_x_preferred_placetype":[
        "municipality"
    ],
    "name:eng_x_preferred":[
        "Lekinioch"
    ],
    "name:fra_x_preferred":[
        "Lekinioch"
    ],
    "name:und_x_variant":[
        "Lukunor"
    ],
    "qs:name":"Lekinioch Municipality",
    "qs:photos_9r":0,
    "qs:photos_sr":0,
    "qs:pop_sr":"2",
    "wof:name":"Lekinioch",
    "wof:placetype":"county",
    "wof:population":927
},
  "geometry": {"coordinates":[153.81899999999999,5.507],"type":"Point"}
}