{
  "type": "Feature",
  "properties": {
    "gn:admin1_code":"03",
    "gn:admin2_code":"DU",
    "gn:asciiname":"Tonoas Municipal Building",
    "gn:country_code":"FM",
    "gn:dem":25,
    "gn:elevation":"8.0",
    "gn:feature_class":"P",
    "gn:feature_code":"PPLA2",
    "gn:name":"Tonoas Municipal Building",
    "gn:population":0,
    "gn:timezone":"Pacific/Chuuk",
    "iso:country":"FM",
    "wof:name":"Tonoas Municipal Building",
    "wof:placetype":"locality"
},
  "geometry": {"coordinates":[151.88433000000001,7.37597],"type":"Point"}
}