{
  "type": "Feature",
  "properties": {
    "gn:admin1_code":"03",
    "gn:admin2_code":"MN",
    "gn:asciiname":"Nukanap",
    "gn:country_code":"FM",
    "gn:dem":6,
    "gn:elevation":"5.0",
    "gn:feature_class":"P",
    "gn:feature_code":"PPL",
    "gn:name":"Nukanap",
    "gn:population":0,
    "gn:timezone":"Pacific/Chuuk",
    "iso:country":"FM",
    "wof:name":"Nukanap",
    "wof:placetype":"locality"
},
  "geometry": {"coordinates":[151.88041999999999,7.44375],"type":"Point"}
}