{
  "type": "Feature",
  "properties": {
    "gn:admin1_code":"02",
    "gn:admin2_code":"MO",
    "gn:asciiname":"Mokil",
    "gn:country_code":"FM",
    "gn:dem":8,
    "gn:feature_class":"P",
    "gn:feature_code":"PPLA2",
    "gn:name":"Mokil",
    "gn:population":0,
    "gn:timezone":"Pacific/Pohnpei",
    "iso:country":"FM",
    "name:ceb_x_preferred":[
        "Mokil"
    ],
    "name:fas_x_preferred":[
        "\u0645\u0648\u06a9\u06cc\u0644"
    ],
    "name:mkd_x_preferred":[
        "\u041c\u043e\u043a\u0438\u043b"
    ],
    "name:nld_x_preferred":[
        "Mokil"
    ],
    "name:por_x_preferred":[
        "Mokil"
    ],
    "name:swe_x_preferred":[
        "Mokil"
    ],
    "wof:name":"Mokil",
    "wof:placetype":"locality"
},
  "geometry": {"coordinates":[159.76283000000001,6.69281],"type":"Point"}
}