{
  "type": "Feature",
  "properties": {
    "gn:country":"FM",
    "gn:fcode":"PPL",
    "gn:pop":192,
    "iso:country":"FM",
    "name:cat_x_preferred":[
        "Pavlopetri"
    ],
    "name:deu_x_preferred":[
        "Pavlopetri"
    ],
    "name:ell_x_preferred":[
        "\u03a0\u03b1\u03c5\u03bb\u03bf\u03c0\u03ad\u03c4\u03c1\u03b9"
    ],
    "name:epo_x_preferred":[
        "Pavlopetri"
    ],
    "name:fin_x_preferred":[
        "Pavlop\u00e9tri"
    ],
    "name:fra_x_preferred":[
        "Pavlopetri"
    ],
    "name:ita_x_preferred":[
        "Pavlopetri"
    ],
    "name:lat_x_preferred":[
        "Paulopetrium"
    ],
    "name:nld_x_preferred":[
        "Pavlopetri"
    ],
    "name:pol_x_preferred":[
        "Pawlopetri"
    ],
    "name:por_x_preferred":[
        "Pavlopetri"
    ],
    "name:spa_x_preferred":[
        "Pavlopetri"
    ],
    "name:unk_x_variant":[
        "Ono Village"
    ],
    "qs:name":"Onou Village",
    "qs:photos_9r":0,
    "qs:photos_sr":0,
    "qs:pop_sr":"1",
    "wd:wordcount":803,
    "wof:name":"Onou Village",
    "wof:placetype":"locality",
    "wof:population":192
},
  "geometry": {"coordinates":[150.29249999999999,8.79641],"type":"Point"}
}