{
  "type": "Feature",
  "properties": {
    "gn:country":"FM",
    "gn:fcode":"PPL",
    "gn:pop":192,
    "iso:country":"FM",
    "name:unk_x_variant":[
        "Ono Village"
    ],
    "qs:name":"Onou Village",
    "qs:photos_9r":0,
    "qs:photos_sr":0,
    "qs:pop_sr":"1",
    "wd:wordcount":803,
    "wof:name":"Onou Village",
    "wof:placetype":"locality",
    "wof:population":192
},
  "geometry": {"coordinates":[150.29249999999999,8.79641],"type":"Point"}
}