{
  "type": "Feature",
  "properties": {
    "gn:admin1_code":"04",
    "gn:admin2_code":"WO",
    "gn:asciiname":"Wottegai",
    "gn:country_code":"FM",
    "gn:dem":8,
    "gn:feature_class":"P",
    "gn:feature_code":"PPL",
    "gn:name":"Wottegai",
    "gn:population":0,
    "gn:timezone":"Pacific/Chuuk",
    "iso:country":"FM",
    "wof:name":"Wottegai",
    "wof:placetype":"locality"
},
  "geometry": {"coordinates":[143.83772999999999,7.37166],"type":"Point"}
}