{
  "type": "Feature",
  "properties": {
    "gn:country":"FM",
    "gn:fcode":"ADM2",
    "gn:population":365,
    "iso:country":"FM",
    "label:eng_x_preferred_longname":[
        "Tamatam Municipality"
    ],
    "label:eng_x_preferred_placetype":[
        "municipality"
    ],
    "name:bul_x_preferred":[
        "\u0422\u0430\u043c\u0430\u0442\u0430\u043c"
    ],
    "name:ceb_x_preferred":[
        "Tamatam"
    ],
    "name:eng_x_preferred":[
        "Tamatam"
    ],
    "name:fas_x_preferred":[
        "\u062a\u0627\u0645\u0627\u062a\u0627\u0645"
    ],
    "name:fra_x_preferred":[
        "Tamatam"
    ],
    "name:ita_x_preferred":[
        "Tamatam"
    ],
    "name:jpn_x_preferred":[
        "\u30bf\u30de\u30bf\u30e0\u5cf6"
    ],
    "name:mkd_x_preferred":[
        "\u0422\u0430\u043c\u0430\u0442\u0430\u043c"
    ],
    "name:nld_x_preferred":[
        "Tamatam"
    ],
    "name:pol_x_preferred":[
        "Tamatam"
    ],
    "name:spa_x_preferred":[
        "Tamatam"
    ],
    "name:swe_x_preferred":[
        "Tamatam"
    ],
    "qs:name":"Tamatam Municipality",
    "qs:photos_9r":0,
    "qs:photos_sr":0,
    "qs:pop_sr":"2",
    "statoids:country":"FM",
    "statoids:hasc":"FM.CH",
    "statoids:name":"Tamatam",
    "statoids:timezone":"10",
    "statoids:type":"municipality",
    "wd:wordcount":126,
    "wof:name":"Tamatam Municipality",
    "wof:placetype":"county",
    "wof:placetype_local":"municipality",
    "wof:population":365,
    "wof:shortcode":"TM"
},
  "geometry": {"coordinates":[149.41175000000001,7.53898],"type":"Point"}
}