{
  "type": "Feature",
  "properties": {
    "gn:country":"FM",
    "gn:fcode":"ADM2",
    "gn:pop":365,
    "iso:country":"FM",
    "name:eng_x_preferred":[
        "Tamatam"
    ],
    "qs:name":"Tamatam Municipality",
    "qs:photos_9r":0,
    "qs:photos_sr":0,
    "qs:pop_sr":"2",
    "statoids:country":"FM",
    "statoids:hasc":"FM.CH",
    "statoids:name":"Tamatam",
    "statoids:timezone":"10",
    "statoids:type":"municipality",
    "wd:wordcount":126,
    "wof:name":"Tamatam Municipality",
    "wof:placetype":"county",
    "wof:placetype_local":"municipality",
    "wof:population":365,
    "wof:shortcode":"TM"
},
  "geometry": {"coordinates":[149.41175000000001,7.53898],"type":"Point"}
}