{
  "type": "Feature",
  "properties": {
    "gn:admin1_code":"03",
    "gn:admin2_code":"MN",
    "gn:asciiname":"Winipis",
    "gn:cc2":"FM",
    "gn:country_code":"FM",
    "gn:dem":5,
    "gn:elevation":"4.0",
    "gn:feature_class":"P",
    "gn:feature_code":"PPL",
    "gn:name":"Winipis",
    "gn:population":0,
    "gn:timezone":"Pacific/Chuuk",
    "iso:country":"FM",
    "name:und_x_variant":[
        "\u014c-iwa",
        "Vinepis",
        "Unipis"
    ],
    "wof:name":"Winipis",
    "wof:placetype":"locality"
},
  "geometry": {"coordinates":[151.88526000000005,7.44533],"type":"Point"}
}