{
  "type": "Feature",
  "properties": {
    "gn:admin1_code":"02",
    "gn:admin2_code":"NE",
    "gn:asciiname":"Niheke",
    "gn:country_code":"FM",
    "gn:dem":24,
    "gn:elevation":"4.0",
    "gn:feature_class":"P",
    "gn:feature_code":"PPL",
    "gn:name":"Niheke",
    "gn:population":0,
    "gn:timezone":"Pacific/Pohnpei",
    "iso:country":"FM",
    "wof:name":"Niheke",
    "wof:placetype":"locality"
},
  "geometry": {"coordinates":[158.23777999999999,6.95761],"type":"Point"}
}