{
  "type": "Feature",
  "properties": {
    "gn:admin1_code":"02",
    "gn:admin2_code":"MA",
    "gn:asciiname":"Kitamw",
    "gn:country_code":"FM",
    "gn:dem":15,
    "gn:elevation":"9.0",
    "gn:feature_class":"P",
    "gn:feature_code":"PPL",
    "gn:name":"Kitamw",
    "gn:population":0,
    "gn:timezone":"Pacific/Pohnpei",
    "iso:country":"FM",
    "wof:name":"Kitamw",
    "wof:placetype":"locality"
},
  "geometry": {"coordinates":[158.29003,6.88627],"type":"Point"}
}