{
  "type": "Feature",
  "properties": {
    "gn:admin1_code":"03",
    "gn:admin2_code":"FF",
    "gn:asciiname":"Feini",
    "gn:country_code":"FM",
    "gn:dem":7,
    "gn:elevation":"3.0",
    "gn:feature_class":"P",
    "gn:feature_code":"PPL",
    "gn:name":"Feini",
    "gn:population":0,
    "gn:timezone":"Pacific/Chuuk",
    "iso:country":"FM",
    "name:und_x_variant":[
        "Fein",
        "Feyin"
    ],
    "wof:name":"Feini",
    "wof:placetype":"locality"
},
  "geometry": {"coordinates":[151.83006,7.34607],"type":"Point"}
}