{
  "type": "Feature",
  "properties": {
    "gn:admin1_code":"03",
    "gn:admin2_code":"MN",
    "gn:asciiname":"Tunuk",
    "gn:country_code":"FM",
    "gn:dem":13,
    "gn:elevation":"4.0",
    "gn:feature_class":"P",
    "gn:feature_code":"PPL",
    "gn:name":"Tunuk",
    "gn:population":0,
    "gn:timezone":"Pacific/Chuuk",
    "iso:country":"FM",
    "name:und_x_variant":[
        "Oror en Nepiepi",
        "Oror En Nepiepi",
        "Oror En Ngesano",
        "Ngasano"
    ],
    "wof:name":"Tunuk",
    "wof:placetype":"locality"
},
  "geometry": {"coordinates":[151.86428999999995,7.45783],"type":"Point"}
}