{
  "type": "Feature",
  "properties": {
    "gn:admin1_code":"03",
    "gn:admin2_code":"MN",
    "gn:asciiname":"Iras",
    "gn:country_code":"FM",
    "gn:dem":6,
    "gn:elevation":"8.0",
    "gn:feature_class":"P",
    "gn:feature_code":"PPL",
    "gn:name":"Iras",
    "gn:population":0,
    "gn:timezone":"Pacific/Chuuk",
    "iso:country":"FM",
    "name:und_x_variant":[
        "Irras",
        "Iradj"
    ],
    "wof:name":"Iras",
    "wof:placetype":"locality"
},
  "geometry": {"coordinates":[151.84353999999999,7.45843],"type":"Point"}
}