{
  "type": "Feature",
  "properties": {
    "gn:admin1_code":"02",
    "gn:admin2_code":"UH",
    "gn:asciiname":"Sapworo",
    "gn:country_code":"FM",
    "gn:dem":23,
    "gn:elevation":"4.0",
    "gn:feature_class":"P",
    "gn:feature_code":"PPL",
    "gn:name":"Sapworo",
    "gn:population":0,
    "gn:timezone":"Pacific/Pohnpei",
    "iso:country":"FM",
    "wof:name":"Sapworo",
    "wof:placetype":"locality"
},
  "geometry": {"coordinates":[158.28861000000001,6.93787],"type":"Point"}
}