{
  "type": "Feature",
  "properties": {
    "gn:admin1_code":"03",
    "gn:admin2_code":"TS",
    "gn:asciiname":"Nesamo",
    "gn:country_code":"FM",
    "gn:dem":14,
    "gn:elevation":"6.0",
    "gn:feature_class":"P",
    "gn:feature_code":"PPL",
    "gn:name":"Nesamo",
    "gn:population":0,
    "gn:timezone":"Pacific/Chuuk",
    "iso:country":"FM",
    "wof:name":"Nesamo",
    "wof:placetype":"locality"
},
  "geometry": {"coordinates":[151.82498000000001,7.29894],"type":"Point"}
}