{
  "type": "Feature",
  "properties": {
    "gn:country":"FM",
    "gn:fcode":"PPL",
    "gn:population":221,
    "iso:country":"FM",
    "qs_pg:aaroncc":"FM",
    "qs_pg:gn_country":"FM",
    "qs_pg:gn_fcode":"PPL",
    "qs_pg:gn_pop":221,
    "qs_pg:name":"Faraulep Village",
    "qs_pg:photos_9r":0,
    "qs_pg:photos_sr":0,
    "qs_pg:pop_sr":2,
    "qs_pg:qs_pg_placetype":"locality",
    "wof:name":"Faraulep Village",
    "wof:placetype":"locality",
    "wof:population":221
},
  "geometry": {"coordinates":[144.52028999999999,8.58889],"type":"Point"}
}