{
  "type": "Feature",
  "properties": {
    "gn:admin1_code":"02",
    "gn:admin2_code":"KT",
    "gn:asciiname":"Pwel Weita",
    "gn:cc2":"FM",
    "gn:country_code":"FM",
    "gn:dem":15,
    "gn:elevation":"10.0",
    "gn:feature_class":"P",
    "gn:feature_code":"PPL",
    "gn:name":"Pwel Weita",
    "gn:population":0,
    "gn:timezone":"Pacific/Pohnpei",
    "iso:country":"FM",
    "name:und_x_variant":[
        "Palang",
        "Pehleng"
    ],
    "wof:name":"Pwel Weita",
    "wof:placetype":"locality"
},
  "geometry": {"coordinates":[158.16246000000001,6.87027],"type":"Point"}
}