{
  "type": "Feature",
  "properties": {
    "gn:admin1_code":"02",
    "gn:admin2_code":"NE",
    "gn:asciiname":"Pohndimur",
    "gn:country_code":"FM",
    "gn:dem":9,
    "gn:elevation":"4.0",
    "gn:feature_class":"P",
    "gn:feature_code":"PPL",
    "gn:name":"Pohndimur",
    "gn:population":0,
    "gn:timezone":"Pacific/Pohnpei",
    "iso:country":"FM",
    "name:und_x_variant":[
        "Pohndimw"
    ],
    "wof:name":"Pohndimur",
    "wof:placetype":"locality"
},
  "geometry": {"coordinates":[158.23808,6.95925],"type":"Point"}
}