{
  "type": "Feature",
  "properties": {
    "gn:admin1_code":"02",
    "gn:admin2_code":"SO",
    "gn:asciiname":"Pakin Village",
    "gn:country_code":"FM",
    "gn:dem":-9999,
    "gn:feature_class":"P",
    "gn:feature_code":"PPL",
    "gn:name":"Pakin Village",
    "gn:population":0,
    "gn:timezone":"Pacific/Pohnpei",
    "iso:country":"FM",
    "wof:name":"Pakin Village",
    "wof:placetype":"locality"
},
  "geometry": {"coordinates":[157.77635000000001,7.07651],"type":"Point"}
}