{
  "type": "Feature",
  "properties": {
    "gn:admin1_code":"03",
    "gn:admin2_code":"DU",
    "gn:asciiname":"Sapou",
    "gn:cc2":"FM",
    "gn:country_code":"FM",
    "gn:dem":45,
    "gn:elevation":"30.0",
    "gn:feature_class":"P",
    "gn:feature_code":"PPL",
    "gn:name":"Sapou",
    "gn:population":0,
    "gn:timezone":"Pacific/Chuuk",
    "iso:country":"FM",
    "name:und_x_variant":[
        "Sopou",
        "Sobou"
    ],
    "wof:name":"Sapou",
    "wof:placetype":"locality"
},
  "geometry": {"coordinates":[151.89178000000001,7.38764],"type":"Point"}
}