{
  "type": "Feature",
  "properties": {
    "gn:admin1_code":"04",
    "gn:admin2_code":"RL",
    "gn:asciiname":"Tabnifiy",
    "gn:cc2":"FM",
    "gn:country_code":"FM",
    "gn:dem":16,
    "gn:elevation":"15.0",
    "gn:feature_class":"P",
    "gn:feature_code":"PPL",
    "gn:name":"Tabnifiy",
    "gn:population":0,
    "gn:timezone":"Pacific/Chuuk",
    "iso:country":"FM",
    "name:und_x_variant":[
        "Tabunifi"
    ],
    "wof:name":"Tabnifiy",
    "wof:placetype":"locality"
},
  "geometry": {"coordinates":[138.06968999999998,9.47133],"type":"Point"}
}