{
  "type": "Feature",
  "properties": {
    "gn:admin1_code":"02",
    "gn:admin2_code":"UH",
    "gn:asciiname":"Mesenpal",
    "gn:country_code":"FM",
    "gn:dem":26,
    "gn:elevation":"3.0",
    "gn:feature_class":"P",
    "gn:feature_code":"PPL",
    "gn:name":"Mesenpal",
    "gn:population":0,
    "gn:timezone":"Pacific/Pohnpei",
    "iso:country":"FM",
    "name:und_x_variant":[
        "Mesenpali"
    ],
    "wof:name":"Mesenpal",
    "wof:placetype":"locality"
},
  "geometry": {"coordinates":[158.25441999999995,6.96951],"type":"Point"}
}