{
  "type": "Feature",
  "properties": {
    "gn:admin1_code":"02",
    "gn:admin2_code":"OR",
    "gn:asciiname":"Kapingamarangi Settlement not permanent",
    "gn:country_code":"FM",
    "gn:dem":12,
    "gn:feature_class":"P",
    "gn:feature_code":"PPL",
    "gn:name":"Kapingamarangi Settlement not permanent",
    "gn:population":0,
    "gn:timezone":"Pacific/Pohnpei",
    "iso:country":"FM",
    "wof:name":"Kapingamarangi Settlement not permanent",
    "wof:placetype":"locality"
},
  "geometry": {"coordinates":[155.15974,7.61963],"type":"Point"}
}