{
  "type": "Feature",
  "properties": {
    "gn:admin1_code":"01",
    "gn:admin2_code":"TA",
    "gn:asciiname":"Walung",
    "gn:country_code":"FM",
    "gn:dem":8,
    "gn:elevation":"4.0",
    "gn:feature_class":"P",
    "gn:feature_code":"PPL",
    "gn:name":"Walung",
    "gn:population":0,
    "gn:timezone":"Pacific/Kosrae",
    "iso:country":"FM",
    "name:und_x_variant":[
        "former Walung Municipality",
        "Inshiappu"
    ],
    "wof:name":"Walung",
    "wof:placetype":"locality"
},
  "geometry": {"coordinates":[162.91528,5.30778],"type":"Point"}
}