{
  "type": "Feature",
  "properties": {
    "gn:admin1_code":"04",
    "gn:admin2_code":"WO",
    "gn:asciiname":"Woleai Village",
    "gn:country_code":"FM",
    "gn:dem":10,
    "gn:feature_class":"P",
    "gn:feature_code":"PPL",
    "gn:name":"Woleai Village",
    "gn:population":0,
    "gn:timezone":"Pacific/Chuuk",
    "iso:country":"FM",
    "wof:name":"Woleai Village",
    "wof:placetype":"locality"
},
  "geometry": {"coordinates":[143.90433999999999,7.37042],"type":"Point"}
}