{
  "type": "Feature",
  "properties": {
    "gn:country":"FM",
    "gn:fcode":"ISL",
    "gn:population":215,
    "iso:country":"FM",
    "name:ceb_x_preferred":[
        "Fais Island"
    ],
    "name:deu_x_preferred":[
        "Fais"
    ],
    "name:eng_x_preferred":[
        "Fais Island"
    ],
    "name:fas_x_preferred":[
        "\u0641\u0627\u06cc\u0633"
    ],
    "name:fin_x_preferred":[
        "Fais"
    ],
    "name:fra_x_preferred":[
        "Fais"
    ],
    "name:ita_x_preferred":[
        "Fais"
    ],
    "name:jpn_x_preferred":[
        "\u30d5\u30a1\u30a4\u30b9\u5cf6"
    ],
    "name:mkd_x_preferred":[
        "\u0424\u0430\u0438\u0441"
    ],
    "name:nld_x_preferred":[
        "Fais Island"
    ],
    "name:pol_x_preferred":[
        "Fais"
    ],
    "name:spa_x_preferred":[
        "Isla Fais"
    ],
    "name:swe_x_preferred":[
        "Fais Island"
    ],
    "name:tam_x_preferred":[
        "\u0b83\u0baa\u0bc8\u0b9a\u0bc1 \u0ba4\u0bc0\u0bb5\u0bc1"
    ],
    "name:und_x_variant":[
        "Astrolabe"
    ],
    "name:zho_x_preferred":[
        "\u6cd5\u65af\u5cf6"
    ],
    "qs:name":"Fais Island",
    "qs:photos_9r":0,
    "qs:photos_sr":0,
    "qs:pop_sr":"2",
    "wd:wordcount":737,
    "wof:name":"Fais Island",
    "wof:placetype":"locality",
    "wof:population":215
},
  "geometry": {"coordinates":[140.51949999999999,9.766],"type":"Point"}
}