{
  "type": "Feature",
  "properties": {
    "gn:country":"FM",
    "gn:fcode":"ISL",
    "gn:pop":215,
    "iso:country":"FM",
    "name:unk_x_variant":[
        "Astrolabe"
    ],
    "qs:name":"Fais Island",
    "qs:photos_9r":0,
    "qs:photos_sr":0,
    "qs:pop_sr":"2",
    "wd:wordcount":737,
    "wof:name":"Fais Island",
    "wof:placetype":"locality",
    "wof:population":215
},
  "geometry": {"coordinates":[140.51949999999999,9.766],"type":"Point"}
}