{
  "type": "Feature",
  "properties": {
    "gn:country":"FM",
    "gn:fcode":"ADM2",
    "gn:population":221,
    "iso:country":"FM",
    "label:eng_x_preferred_longname":[
        "Faraulep Municipality"
    ],
    "label:eng_x_preferred_placetype":[
        "municipality"
    ],
    "name:bul_x_preferred":[
        "\u0424\u0430\u0440\u0430\u0443\u043b\u0435\u043f"
    ],
    "name:ceb_x_preferred":[
        "Faraulep"
    ],
    "name:deu_x_preferred":[
        "Faraulep"
    ],
    "name:eng_x_preferred":[
        "Faraulep"
    ],
    "name:fas_x_preferred":[
        "\u0641\u0627\u0631\u0627\u0626\u0648\u0644\u067e"
    ],
    "name:fra_x_preferred":[
        "Faraulep"
    ],
    "name:ita_x_preferred":[
        "Faraulep"
    ],
    "name:jpn_x_preferred":[
        "\u30d5\u30a1\u30e9\u30a6\u30ec\u30c3\u30d7\u74b0\u7901"
    ],
    "name:lav_x_preferred":[
        "Faraulepa"
    ],
    "name:nld_x_preferred":[
        "Faraulep"
    ],
    "name:rus_x_preferred":[
        "\u0424\u0430\u0440\u0430\u0443\u043b\u0435\u043f"
    ],
    "name:spa_x_preferred":[
        "Faraulep"
    ],
    "name:swe_x_preferred":[
        "Faraulep"
    ],
    "name:tur_x_preferred":[
        "Faraulep"
    ],
    "name:und_x_variant":[
        "Faraulap"
    ],
    "name:zho_x_preferred":[
        "\u6cd5\u52de\u840a\u666e\u74b0\u7901"
    ],
    "qs:name":"Faraulep Municipality",
    "qs:photos_9r":0,
    "qs:photos_sr":0,
    "qs:pop_sr":"2",
    "statoids:country":"FM",
    "statoids:hasc":"FM.YA",
    "statoids:name":"Faraulep",
    "statoids:timezone":"10",
    "statoids:type":"municipality",
    "wd:wordcount":258,
    "wof:name":"Faraulep Municipality",
    "wof:placetype":"county",
    "wof:placetype_local":"municipality",
    "wof:population":221,
    "wof:shortcode":"FP"
},
  "geometry": {"coordinates":[144.50649999999999,8.588],"type":"Point"}
}