{
  "type": "Feature",
  "properties": {
    "gn:country":"FM",
    "gn:fcode":"ADM2",
    "gn:pop":221,
    "iso:country":"FM",
    "label:eng_x_preferred_longname":[
        "Faraulep Municipality"
    ],
    "label:eng_x_preferred_placetype":[
        "municipality"
    ],
    "name:eng_x_preferred":[
        "Faraulep"
    ],
    "name:unk_x_variant":[
        "Faraulap"
    ],
    "qs:name":"Faraulep Municipality",
    "qs:photos_9r":0,
    "qs:photos_sr":0,
    "qs:pop_sr":"2",
    "statoids:country":"FM",
    "statoids:hasc":"FM.YA",
    "statoids:name":"Faraulep",
    "statoids:timezone":"10",
    "statoids:type":"municipality",
    "wd:wordcount":258,
    "wof:name":"Faraulep Municipality",
    "wof:placetype":"county",
    "wof:placetype_local":"municipality",
    "wof:population":221,
    "wof:shortcode":"FP"
},
  "geometry": {"coordinates":[144.50649999999999,8.588],"type":"Point"}
}