{
  "type": "Feature",
  "properties": {
    "gn:admin1_code":"02",
    "gn:admin2_code":"KP",
    "gn:asciiname":"Kapingamarangi",
    "gn:country_code":"FM",
    "gn:dem":11,
    "gn:feature_class":"P",
    "gn:feature_code":"PPLA2",
    "gn:name":"Kapingamarangi",
    "gn:population":0,
    "gn:timezone":"Pacific/Pohnpei",
    "iso:country":"FM",
    "wof:name":"Kapingamarangi",
    "wof:placetype":"locality"
},
  "geometry": {"coordinates":[154.80751999999995,1.07861],"type":"Point"}
}