{
  "type": "Feature",
  "properties": {
    "gn:admin1_code":"02",
    "gn:admin2_code":"KP",
    "gn:asciiname":"Kapingamarangi",
    "gn:country_code":"FM",
    "gn:dem":11,
    "gn:feature_class":"P",
    "gn:feature_code":"PPLA2",
    "gn:name":"Kapingamarangi",
    "gn:population":0,
    "gn:timezone":"Pacific/Pohnpei",
    "iso:country":"FM",
    "name:ace_x_preferred":[
        "Kapingamarangi"
    ],
    "name:ara_x_preferred":[
        "\u0643\u0627\u0628\u064a\u0646\u062c\u0627\u0645\u0627\u0631\u0627\u0646\u062c\u064a"
    ],
    "name:bel_x_preferred":[
        "\u041a\u0430\u043f\u0456\u043d\u0433\u0430\u043c\u0430\u0440\u0430\u043d\u0433\u0456"
    ],
    "name:cat_x_preferred":[
        "Kapingamarangi"
    ],
    "name:ces_x_preferred":[
        "Kapingamarangi"
    ],
    "name:deu_x_preferred":[
        "Kapingamarangi"
    ],
    "name:fas_x_preferred":[
        "\u06a9\u0627\u067e\u06cc\u0646\u0627\u0645\u0627\u0631\u0646\u06af\u06cc"
    ],
    "name:fin_x_preferred":[
        "Kapingamarangi"
    ],
    "name:fra_x_preferred":[
        "Kapingamarangi"
    ],
    "name:ita_x_preferred":[
        "Kapingamarangi"
    ],
    "name:jpn_x_preferred":[
        "\u30ab\u30d4\u30f3\u30ac\u30de\u30e9\u30f3\u30ae\u74b0\u7901"
    ],
    "name:kor_x_preferred":[
        "\uce74\ud551\uc544\ub9c8\ub791\uc774 \ud658\ucd08"
    ],
    "name:lat_x_preferred":[
        "Kapingamarangi"
    ],
    "name:lit_x_preferred":[
        "Kapingamarangis"
    ],
    "name:mkd_x_preferred":[
        "\u041a\u0430\u043f\u0438\u043d\u0433\u0430\u043c\u0430\u0440\u0430\u043d\u0433\u0438"
    ],
    "name:nld_x_preferred":[
        "Kapingamarangi"
    ],
    "name:rus_x_preferred":[
        "\u041a\u0430\u043f\u0438\u043d\u0433\u0430\u043c\u0430\u0440\u0430\u043d\u0433\u0438"
    ],
    "name:spa_x_preferred":[
        "Kapingamarangi"
    ],
    "name:ukr_x_preferred":[
        "\u041a\u0430\u043f\u0456\u043d\u0433\u0430\u043c\u0430\u0440\u0430\u043d\u0433\u0456"
    ],
    "name:zho_x_preferred":[
        "\u5361\u5e73\u963f\u99ac\u6717\u4f0a\u74b0\u7901"
    ],
    "wof:name":"Kapingamarangi",
    "wof:placetype":"locality"
},
  "geometry": {"coordinates":[154.80751999999995,1.07861],"type":"Point"}
}