{
  "type": "Feature",
  "properties": {
    "gn:admin1_code":"03",
    "gn:admin2_code":"PN",
    "gn:asciiname":"Nepanonong",
    "gn:country_code":"FM",
    "gn:dem":9,
    "gn:elevation":"2.0",
    "gn:feature_class":"P",
    "gn:feature_code":"PPL",
    "gn:name":"Nepanonong",
    "gn:population":0,
    "gn:timezone":"Pacific/Chuuk",
    "iso:country":"FM",
    "name:und_x_variant":[
        "Oror En Nipanonong"
    ],
    "wof:name":"Nepanonong",
    "wof:placetype":"locality"
},
  "geometry": {"coordinates":[151.58725000000001,7.32612],"type":"Point"}
}