{
  "type": "Feature",
  "properties": {
    "gn:country":"FM",
    "gn:fcode":"PPL",
    "gn:population":339,
    "iso:country":"FM",
    "name:ceb_x_preferred":[
        "State of Yap"
    ],
    "name:deu_x_preferred":[
        "Yap"
    ],
    "name:fas_x_preferred":[
        "\u0627\u06cc\u0627\u0644\u062a \u06cc\u0627\u067e"
    ],
    "name:fin_x_preferred":[
        "Yapin osavaltio"
    ],
    "name:fra_x_preferred":[
        "Yap"
    ],
    "name:hin_x_preferred":[
        "\u092f\u093e\u092a \u0930\u093e\u091c\u094d\u092f"
    ],
    "name:jpn_x_preferred":[
        "\u30e4\u30c3\u30d7\u5dde"
    ],
    "name:kat_x_preferred":[
        "\u10d8\u10d0\u10de\u10d8"
    ],
    "name:kor_x_preferred":[
        "\uc57c\ud504\uc8fc"
    ],
    "name:pol_x_preferred":[
        "Yap"
    ],
    "name:rus_x_preferred":[
        "\u042f\u043f"
    ],
    "name:ukr_x_preferred":[
        "\u042f\u043f"
    ],
    "name:urd_x_preferred":[
        "\u0631\u06cc\u0627\u0633\u062a \u06cc\u0627\u067e"
    ],
    "name:zho_x_preferred":[
        "\u96c5\u6d66\u5dde"
    ],
    "qs:name":"Lamotrek Village",
    "qs:photos_9r":0,
    "qs:photos_sr":0,
    "qs:pop_sr":"2",
    "wd:wordcount":188,
    "wof:name":"Lamotrek Village",
    "wof:placetype":"locality",
    "wof:population":339
},
  "geometry": {"coordinates":[146.37841,7.45758],"type":"Point"}
}