{
  "type": "Feature",
  "properties": {
    "gn:country":"FM",
    "gn:fcode":"PPL",
    "gn:pop":339,
    "iso:country":"FM",
    "qs:name":"Lamotrek Village",
    "qs:photos_9r":0,
    "qs:photos_sr":0,
    "qs:pop_sr":"2",
    "wd:wordcount":188,
    "wof:name":"Lamotrek Village",
    "wof:placetype":"locality",
    "wof:population":339
},
  "geometry": {"coordinates":[146.37841,7.45758],"type":"Point"}
}