{
  "type": "Feature",
  "properties": {
    "gn:country":"FM",
    "gn:fcode":"ADMF",
    "gn:pop":13802,
    "iso:country":"FM",
    "qs:name":"Weno - Chuuk State Legislature",
    "qs:photos_9r":0,
    "qs:photos_sr":0,
    "qs:pop_sr":"6",
    "wof:name":"Weno - Chuuk State Legislature",
    "wof:placetype":"locality",
    "wof:population":13802
},
  "geometry": {"coordinates":[151.84345999999999,7.4564],"type":"Point"}
}