{
  "type": "Feature",
  "properties": {
    "gn:admin1_code":"03",
    "gn:admin2_code":"MA",
    "gn:asciiname":"Makur",
    "gn:country_code":"FM",
    "gn:dem":10,
    "gn:feature_class":"P",
    "gn:feature_code":"PPLA2",
    "gn:name":"Makur",
    "gn:population":0,
    "gn:timezone":"Pacific/Chuuk",
    "iso:country":"FM",
    "wof:name":"Makur",
    "wof:placetype":"locality"
},
  "geometry": {"coordinates":[150.1275,8.985],"type":"Point"}
}