{
  "type": "Feature",
  "properties": {
    "gn:country":"FM",
    "gn:fcode":"ISL",
    "gn:population":245,
    "iso:country":"FM",
    "name:bul_x_preferred":[
        "\u041f\u0438\u0441\u0430\u0440\u0430\u0441"
    ],
    "name:ceb_x_preferred":[
        "Pisaras"
    ],
    "name:eng_x_preferred":[
        "Pisaras"
    ],
    "name:fas_x_preferred":[
        "\u067e\u06cc\u0633\u0627\u0631\u0627\u0633"
    ],
    "name:fra_x_preferred":[
        "Piherarh"
    ],
    "name:ita_x_preferred":[
        "Piherarh"
    ],
    "name:jpn_x_preferred":[
        "\u30d4\u30d8\u30e9\u30eb\u5cf6"
    ],
    "name:mkd_x_preferred":[
        "\u041f\u0438\u0441\u0430\u0440\u0430\u0441"
    ],
    "name:nld_x_preferred":[
        "Pisaras"
    ],
    "name:por_x_preferred":[
        "Pisaras"
    ],
    "name:spa_x_preferred":[
        "Pisaras"
    ],
    "name:swe_x_preferred":[
        "Pisaras"
    ],
    "name:und_x_variant":[
        "Aronia Island"
    ],
    "qs:name":"Pisaras",
    "qs:photos_9r":0,
    "qs:photos_sr":0,
    "qs:pop_sr":"2",
    "wd:wordcount":40,
    "wof:name":"Pisaras",
    "wof:placetype":"locality",
    "wof:population":245
},
  "geometry": {"coordinates":[150.41849999999999,8.569],"type":"Point"}
}