{
  "type": "Feature",
  "properties": {
    "gn:country":"FM",
    "gn:fcode":"ISLX",
    "gn:population":1271,
    "iso:country":"FM",
    "qs:name":"North Wonei Island",
    "qs:photos_9r":0,
    "qs:photos_sr":0,
    "qs:pop_sr":"3",
    "wof:name":"North Wonei Island",
    "wof:placetype":"locality",
    "wof:population":1271
},
  "geometry": {"coordinates":[151.60249999999999,7.387],"type":"Point"}
}