{
  "type": "Feature",
  "properties": {
    "gn:country":"FM",
    "gn:fcode":"ADM2",
    "gn:population":1271,
    "iso:country":"FM",
    "label:eng_x_preferred_longname":[
        "Oneisom Municipality"
    ],
    "label:eng_x_preferred_placetype":[
        "municipality"
    ],
    "name:eng_x_preferred":[
        "Oneisom"
    ],
    "name:eng_x_variant":[
        "Oneisom Municipality"
    ],
    "name:fra_x_preferred":[
        "Wonei"
    ],
    "qs:name":"Oneisom Municipality",
    "qs:photos_9r":0,
    "qs:photos_sr":0,
    "qs:pop_sr":"3",
    "wof:name":"Oneisom",
    "wof:placetype":"county",
    "wof:population":1271
},
  "geometry": {"coordinates":[151.601,7.387],"type":"Point"}
}