{
  "type": "Feature",
  "properties": {
    "gn:country":"FM",
    "gn:fcode":"ADM2",
    "gn:pop":1271,
    "iso:country":"FM",
    "qs:name":"Oneisom Municipality",
    "qs:photos_9r":0,
    "qs:photos_sr":0,
    "qs:pop_sr":"3",
    "wof:name":"Oneisom Municipality",
    "wof:placetype":"county",
    "wof:population":1271
},
  "geometry": {"coordinates":[151.601,7.387],"type":"Point"}
}