{
  "type": "Feature",
  "properties": {
    "gn:admin1_code":"04",
    "gn:admin2_code":"DA",
    "gn:asciiname":"Binaew",
    "gn:country_code":"FM",
    "gn:dem":16,
    "gn:elevation":"3.0",
    "gn:feature_class":"P",
    "gn:feature_code":"PPL",
    "gn:name":"Binaew",
    "gn:population":0,
    "gn:timezone":"Pacific/Chuuk",
    "iso:country":"FM",
    "name:und_x_variant":[
        "Vinau",
        "Binau",
        "Binaw"
    ],
    "wof:name":"Binaew",
    "wof:placetype":"locality"
},
  "geometry": {"coordinates":[138.08543999999998,9.53137],"type":"Point"}
}