{
  "type": "Feature",
  "properties": {
    "gn:country":"FM",
    "gn:fcode":"RGN",
    "gn:pop":4062,
    "iso:country":"FM",
    "qs:name":"Southern Nomoneas Islands - Fefan Island",
    "qs:photos_9r":0,
    "qs:photos_sr":0,
    "qs:pop_sr":"4",
    "wof:name":"Southern Nomoneas Islands - Fefan Island",
    "wof:placetype":"locality",
    "wof:population":4062
},
  "geometry": {"coordinates":[151.83199999999999,7.353],"type":"Point"}
}