{
  "type": "Feature",
  "properties": {
    "gn:admin1_code":"03",
    "gn:admin2_code":"PK",
    "gn:asciiname":"Houk",
    "gn:country_code":"FM",
    "gn:dem":8,
    "gn:feature_class":"P",
    "gn:feature_code":"PPLA2",
    "gn:name":"Houk",
    "gn:population":0,
    "gn:timezone":"Pacific/Chuuk",
    "iso:country":"FM",
    "wof:name":"Houk",
    "wof:placetype":"locality"
},
  "geometry": {"coordinates":[149.29908,6.6894],"type":"Point"}
}