{
  "type": "Feature",
  "properties": {
    "gn:country":"FM",
    "gn:fcode":"PPL",
    "gn:pop":253,
    "iso:country":"FM",
    "name:fra_x_preferred":[
        "Dabayin"
    ],
    "name:mya_x_preferred":[
        "\u1012\u102e\u1015\u1032\u101a\u1004\u103a\u1038\u1019\u103c\u102d\u102f\u1037"
    ],
    "qs:name":"Ta Village",
    "qs:photos_9r":0,
    "qs:photos_sr":0,
    "qs:pop_sr":"2",
    "wd:wordcount":651,
    "wof:name":"Ta Village",
    "wof:placetype":"locality",
    "wof:population":253
},
  "geometry": {"coordinates":[153.64850000000001,5.2842],"type":"Point"}
}