{
  "type": "Feature",
  "properties": {
    "gn:country":"FM",
    "gn:fcode":"PPL",
    "gn:pop":215,
    "iso:country":"FM",
    "name:cat_x_preferred":[
        "En mai"
    ],
    "name:deu_x_preferred":[
        "En mai"
    ],
    "name:ita_x_preferred":[
        "Accada quel che accada"
    ],
    "name:por_x_preferred":[
        "En mai"
    ],
    "qs:name":"Fais Village",
    "qs:photos_9r":0,
    "qs:photos_sr":0,
    "qs:pop_sr":"2",
    "wd:wordcount":343,
    "wof:name":"Fais Village",
    "wof:placetype":"locality",
    "wof:population":215
},
  "geometry": {"coordinates":[140.51421999999999,9.75612],"type":"Point"}
}