{
  "type": "Feature",
  "properties": {
    "gn:country":"FM",
    "gn:fcode":"ISLS",
    "gn:pop":156,
    "iso:country":"FM",
    "name:unk_x_variant":[
        "Magur Islands"
    ],
    "qs:name":"Makur Islands",
    "qs:photos_9r":0,
    "qs:photos_sr":0,
    "qs:pop_sr":"1",
    "wof:name":"Makur Islands",
    "wof:placetype":"locality",
    "wof:population":156
},
  "geometry": {"coordinates":[150.12649999999999,8.985],"type":"Point"}
}