{
  "type": "Feature",
  "properties": {
    "gn:admin1_code":"04",
    "gn:admin2_code":"RM",
    "gn:asciiname":"Faal",
    "gn:country_code":"FM",
    "gn:dem":10,
    "gn:feature_class":"P",
    "gn:feature_code":"PPL",
    "gn:name":"Faal",
    "gn:population":0,
    "gn:timezone":"Pacific/Chuuk",
    "iso:country":"FM",
    "wof:name":"Faal",
    "wof:placetype":"locality"
},
  "geometry": {"coordinates":[138.15992,9.62381],"type":"Point"}
}