{
  "type": "Feature",
  "properties": {
    "gn:admin1_code":"03",
    "gn:admin2_code":"MN",
    "gn:asciiname":"Wichap",
    "gn:country_code":"FM",
    "gn:dem":31,
    "gn:elevation":"31.0",
    "gn:feature_class":"P",
    "gn:feature_code":"PPL",
    "gn:name":"Wichap",
    "gn:population":0,
    "gn:timezone":"Pacific/Chuuk",
    "iso:country":"FM",
    "name:und_x_variant":[
        "Vidjap"
    ],
    "wof:name":"Wichap",
    "wof:placetype":"locality"
},
  "geometry": {"coordinates":[151.85992999999999,7.42417],"type":"Point"}
}