{
  "type": "Feature",
  "properties": {
    "gn:admin1_code":"02",
    "gn:admin2_code":"UH",
    "gn:asciiname":"Nihkaras",
    "gn:country_code":"FM",
    "gn:dem":25,
    "gn:elevation":"4.0",
    "gn:feature_class":"P",
    "gn:feature_code":"PPL",
    "gn:name":"Nihkaras",
    "gn:population":0,
    "gn:timezone":"Pacific/Pohnpei",
    "iso:country":"FM",
    "wof:name":"Nihkaras",
    "wof:placetype":"locality"
},
  "geometry": {"coordinates":[158.29478999999995,6.95294],"type":"Point"}
}