{
  "type": "Feature",
  "properties": {
    "gn:admin1_code":"02",
    "gn:admin2_code":"KT",
    "gn:asciiname":"Pohnseiuh",
    "gn:country_code":"FM",
    "gn:dem":107,
    "gn:elevation":"105.0",
    "gn:feature_class":"P",
    "gn:feature_code":"PPL",
    "gn:name":"Pohnseiuh",
    "gn:population":0,
    "gn:timezone":"Pacific/Pohnpei",
    "iso:country":"FM",
    "wof:name":"Pohnseiuh",
    "wof:placetype":"locality"
},
  "geometry": {"coordinates":[158.21697,6.81786],"type":"Point"}
}