{
  "type": "Feature",
  "properties": {
    "gn:admin1_code":"02",
    "gn:admin2_code":"NE",
    "gn:asciiname":"Lehle Mwahu",
    "gn:country_code":"FM",
    "gn:dem":39,
    "gn:elevation":"30.0",
    "gn:feature_class":"P",
    "gn:feature_code":"PPL",
    "gn:name":"Lehle Mwahu",
    "gn:population":0,
    "gn:timezone":"Pacific/Pohnpei",
    "iso:country":"FM",
    "wof:name":"Lehle Mwahu",
    "wof:placetype":"locality"
},
  "geometry": {"coordinates":[158.23654999999999,6.93018],"type":"Point"}
}