{
  "type": "Feature",
  "properties": {
    "gn:admin1_code":"02",
    "gn:admin2_code":"UH",
    "gn:asciiname":"Pahina",
    "gn:country_code":"FM",
    "gn:dem":8,
    "gn:elevation":"4.0",
    "gn:feature_class":"P",
    "gn:feature_code":"PPL",
    "gn:name":"Pahina",
    "gn:population":0,
    "gn:timezone":"Pacific/Pohnpei",
    "iso:country":"FM",
    "wof:name":"Pahina",
    "wof:placetype":"locality"
},
  "geometry": {"coordinates":[158.27736999999999,6.94006],"type":"Point"}
}