{
  "type": "Feature",
  "properties": {
    "gn:country":"FM",
    "gn:fcode":"PPL",
    "gn:pop":505,
    "iso:country":"FM",
    "qs:name":"Oneop Village",
    "qs:photos_9r":0,
    "qs:photos_sr":0,
    "qs:pop_sr":"2",
    "wd:wordcount":492,
    "wof:name":"Oneop Village",
    "wof:placetype":"locality",
    "wof:population":505
},
  "geometry": {"coordinates":[153.71100000000001,5.5066],"type":"Point"}
}