{
  "type": "Feature",
  "properties": {
    "gn:country":"FM",
    "gn:fcode":"PPL",
    "gn:population":505,
    "iso:country":"FM",
    "name:bul_x_preferred":[
        "\u041d\u0430\u043c\u043e\u043b\u0443\u043a"
    ],
    "name:ceb_x_preferred":[
        "Namoluk"
    ],
    "name:deu_x_preferred":[
        "Namoluk"
    ],
    "name:eng_x_preferred":[
        "Namoluk"
    ],
    "name:fas_x_preferred":[
        "\u0646\u0627\u0645\u0648\u0644\u0648\u06a9"
    ],
    "name:fra_x_preferred":[
        "Namoluk"
    ],
    "name:ita_x_preferred":[
        "Namoluk"
    ],
    "name:jpn_x_preferred":[
        "\u30ca\u30e2\u30eb\u30af\u74b0\u7901"
    ],
    "name:lav_x_preferred":[
        "Namoluka"
    ],
    "name:mkd_x_preferred":[
        "\u041d\u0430\u043c\u043e\u043b\u0443\u043a"
    ],
    "name:nld_x_preferred":[
        "Namoluk"
    ],
    "name:swe_x_preferred":[
        "Namoluk"
    ],
    "name:zho_x_preferred":[
        "\u7d0d\u83ab\u9b6f\u514b\u74b0\u7901"
    ],
    "qs:name":"Oneop Village",
    "qs:photos_9r":0,
    "qs:photos_sr":0,
    "qs:pop_sr":"2",
    "wd:wordcount":492,
    "wof:name":"Oneop Village",
    "wof:placetype":"locality",
    "wof:population":505
},
  "geometry": {"coordinates":[153.71100000000001,5.5066],"type":"Point"}
}