{
  "type": "Feature",
  "properties": {
    "gn:country":"FM",
    "gn:fcode":"ADM2",
    "gn:population":427,
    "iso:country":"FM",
    "label:eng_x_preferred_longname":[
        "Piis-Emwar Municipality"
    ],
    "label:eng_x_preferred_placetype":[
        "municipality"
    ],
    "name:eng_x_preferred":[
        "Piis-Emwar"
    ],
    "name:eng_x_variant":[
        "Piis-Emwar Municipality"
    ],
    "name:fra_x_preferred":[
        "Piis-Emwar"
    ],
    "qs:name":"Piis-Emwar Municipality",
    "qs:photos_9r":0,
    "qs:photos_sr":0,
    "qs:pop_sr":"2",
    "wof:name":"Piis-Emwar",
    "wof:placetype":"county",
    "wof:population":427
},
  "geometry": {"coordinates":[152.69999999999999,6.834],"type":"Point"}
}