{
  "type": "Feature",
  "properties": {
    "gn:country":"FM",
    "gn:fcode":"ADM2",
    "gn:population":5129,
    "iso:country":"FM",
    "label:eng_x_preferred_longname":[
        "Tolensom Municipality"
    ],
    "label:eng_x_preferred_placetype":[
        "municipality"
    ],
    "name:eng_x_preferred":[
        "Tolensom"
    ],
    "name:eng_x_variant":[
        "Tolensom Municipality"
    ],
    "name:fra_x_preferred":[
        "Tolensom"
    ],
    "qs:name":"Tolensom Municipality",
    "qs:photos_9r":0,
    "qs:photos_sr":0,
    "qs:pop_sr":"5",
    "wof:name":"Tolensom",
    "wof:placetype":"county",
    "wof:population":5129
},
  "geometry": {"coordinates":[151.62299999999999,7.333],"type":"Point"}
}