{
  "type": "Feature",
  "properties": {
    "gn:admin1_code":"04",
    "gn:admin2_code":"TO",
    "gn:asciiname":"Gargey",
    "gn:cc2":"FM",
    "gn:country_code":"FM",
    "gn:dem":21,
    "gn:elevation":"5.0",
    "gn:feature_class":"P",
    "gn:feature_code":"PPL",
    "gn:name":"Gargey",
    "gn:population":0,
    "gn:timezone":"Pacific/Chuuk",
    "iso:country":"FM",
    "name:und_x_variant":[
        "Gaeregei",
        "Garigej",
        "Garguet",
        "Garguei",
        "Garegei",
        "Garuguuei"
    ],
    "wof:name":"Gargey",
    "wof:placetype":"locality"
},
  "geometry": {"coordinates":[138.12835000000001,9.5571],"type":"Point"}
}