{
  "type": "Feature",
  "properties": {
    "gn:admin1_code":"01",
    "gn:admin2_code":"TA",
    "gn:asciiname":"Tafunsak",
    "gn:country_code":"FM",
    "gn:dem":61,
    "gn:elevation":"4.0",
    "gn:feature_class":"P",
    "gn:feature_code":"PPLA2",
    "gn:name":"Tafunsak",
    "gn:population":0,
    "gn:timezone":"Pacific/Kosrae",
    "iso:country":"FM",
    "wof:name":"Tafunsak",
    "wof:placetype":"locality"
},
  "geometry": {"coordinates":[162.98532,5.3671],"type":"Point"}
}