{
  "type": "Feature",
  "properties": {
    "gn:country":"FM",
    "gn:fcode":"ISL",
    "gn:pop":339,
    "iso:country":"FM",
    "name:unk_x_variant":[
        "Insel Lamutrik"
    ],
    "qs:name":"Lamotrek",
    "qs:photos_9r":0,
    "qs:photos_sr":0,
    "qs:pop_sr":"2",
    "wd:wordcount":318,
    "wof:name":"Lamotrek",
    "wof:placetype":"locality",
    "wof:population":339
},
  "geometry": {"coordinates":[146.38247999999999,7.45745],"type":"Point"}
}