{
  "type": "Feature",
  "properties": {
    "gn:admin1_code":"04",
    "gn:admin2_code":"TO",
    "gn:asciiname":"Bugol",
    "gn:country_code":"FM",
    "gn:dem":8,
    "gn:elevation":"3.0",
    "gn:feature_class":"P",
    "gn:feature_code":"PPL",
    "gn:name":"Bugol",
    "gn:population":0,
    "gn:timezone":"Pacific/Chuuk",
    "iso:country":"FM",
    "name:und_x_variant":[
        "Yugol",
        "Vugol",
        "Bogul"
    ],
    "wof:name":"Bugol",
    "wof:placetype":"locality"
},
  "geometry": {"coordinates":[138.15558999999999,9.51588],"type":"Point"}
}