{
  "type": "Feature",
  "properties": {
    "gn:admin1_code":"02",
    "gn:admin2_code":"UH",
    "gn:asciiname":"Nanpwok",
    "gn:country_code":"FM",
    "gn:dem":12,
    "gn:elevation":"4.0",
    "gn:feature_class":"P",
    "gn:feature_code":"PPL",
    "gn:name":"Nanpwok",
    "gn:population":0,
    "gn:timezone":"Pacific/Pohnpei",
    "iso:country":"FM",
    "wof:name":"Nanpwok",
    "wof:placetype":"locality"
},
  "geometry": {"coordinates":[158.30112,6.94992],"type":"Point"}
}