{
  "type": "Feature",
  "properties": {
    "gn:admin1_code":"04",
    "gn:admin2_code":"DA",
    "gn:asciiname":"Magaaf",
    "gn:country_code":"FM",
    "gn:dem":12,
    "gn:elevation":"3.0",
    "gn:feature_class":"P",
    "gn:feature_code":"PPL",
    "gn:name":"Magaaf",
    "gn:population":0,
    "gn:timezone":"Pacific/Chuuk",
    "iso:country":"FM",
    "wof:name":"Magaaf",
    "wof:placetype":"locality"
},
  "geometry": {"coordinates":[138.08793,9.53164],"type":"Point"}
}