{
  "type": "Feature",
  "properties": {
    "gn:country":"FM",
    "gn:fcode":"ADM2",
    "gn:population":995,
    "iso:country":"FM",
    "label:eng_x_preferred_longname":[
        "Nema Municipality"
    ],
    "label:eng_x_preferred_placetype":[
        "municipality"
    ],
    "name:cat_x_preferred":[
        "Kl\u00ed\u017eska Nem\u00e1"
    ],
    "name:ces_x_preferred":[
        "Kl\u00ed\u017eska Nem\u00e1"
    ],
    "name:deu_x_preferred":[
        "Kl\u00ed\u017eska Nem\u00e1"
    ],
    "name:eng_x_preferred":[
        "Nama"
    ],
    "name:epo_x_preferred":[
        "Kl\u00ed\u017eska Nem\u00e1"
    ],
    "name:eus_x_preferred":[
        "Kl\u00ed\u017eska Nem\u00e1"
    ],
    "name:fra_x_preferred":[
        "Kl\u00ed\u017eska Nem\u00e1"
    ],
    "name:hun_x_preferred":[
        "Kolozsn\u00e9ma"
    ],
    "name:ita_x_preferred":[
        "Kl\u00ed\u017eska Nem\u00e1"
    ],
    "name:msa_x_preferred":[
        "Kl\u00ed\u017eska Nem\u00e1"
    ],
    "name:nld_x_preferred":[
        "Kl\u00ed\u017eska Nem\u00e1"
    ],
    "name:pol_x_preferred":[
        "Kl\u00ed\u017eska Nem\u00e1"
    ],
    "name:ron_x_preferred":[
        "Kl\u00ed\u017eska Nem\u00e1"
    ],
    "name:slk_x_preferred":[
        "Kl\u00ed\u017eska Nem\u00e1"
    ],
    "name:spa_x_preferred":[
        "Kl\u00ed\u017eska Nem\u00e1"
    ],
    "name:srp_x_preferred":[
        "\u041a\u043b\u0438\u0448\u043a\u0430 \u040a\u0435\u043c\u0430"
    ],
    "name:ukr_x_preferred":[
        "\u041a\u043b\u0438\u0436\u0441\u044c\u043a\u0430 \u041d\u0435\u043c\u0430"
    ],
    "name:war_x_preferred":[
        "Kl\u00ed\u017eska Nem\u00e1"
    ],
    "qs:name":"Nema Municipality",
    "qs:photos_9r":0,
    "qs:photos_sr":0,
    "qs:pop_sr":"2",
    "statoids:country":"FM",
    "statoids:hasc":"FM.CH",
    "statoids:name":"Nama",
    "statoids:timezone":"10",
    "statoids:type":"municipality",
    "wd:wordcount":165,
    "wof:name":"Nema Municipality",
    "wof:placetype":"county",
    "wof:placetype_local":"municipality",
    "wof:population":995,
    "wof:shortcode":"NA"
},
  "geometry": {"coordinates":[152.57400000000001,6.993],"type":"Point"}
}