{
  "type": "Feature",
  "properties": {
    "gn:country":"FM",
    "gn:fcode":"ADM2",
    "gn:pop":995,
    "iso:country":"FM",
    "label:eng_x_preferred_longname":[
        "Nema Municipality"
    ],
    "label:eng_x_preferred_placetype":[
        "municipality"
    ],
    "name:eng_x_preferred":[
        "Nama"
    ],
    "name:unk_x_variant":[
        "Nama"
    ],
    "qs:name":"Nema Municipality",
    "qs:photos_9r":0,
    "qs:photos_sr":0,
    "qs:pop_sr":"2",
    "statoids:country":"FM",
    "statoids:hasc":"FM.CH",
    "statoids:name":"Nama",
    "statoids:timezone":"10",
    "statoids:type":"municipality",
    "wd:wordcount":165,
    "wof:name":"Nema Municipality",
    "wof:placetype":"county",
    "wof:placetype_local":"municipality",
    "wof:population":995,
    "wof:shortcode":"NA"
},
  "geometry": {"coordinates":[152.57400000000001,6.993],"type":"Point"}
}