{
  "type": "Feature",
  "properties": {
    "gn:admin1_code":"03",
    "gn:admin2_code":"PN",
    "gn:asciiname":"Neirenom",
    "gn:country_code":"FM",
    "gn:dem":9,
    "gn:elevation":"2.0",
    "gn:feature_class":"P",
    "gn:feature_code":"PPL",
    "gn:name":"Neirenom",
    "gn:population":0,
    "gn:timezone":"Pacific/Chuuk",
    "iso:country":"FM",
    "name:und_x_variant":[
        "Neirenom District"
    ],
    "wof:name":"Neirenom",
    "wof:placetype":"locality"
},
  "geometry": {"coordinates":[151.59225000000001,7.32817],"type":"Point"}
}