{
  "type": "Feature",
  "properties": {
    "gn:admin1_code":"04",
    "gn:admin2_code":"RM",
    "gn:asciiname":"Bulwol - temp LL",
    "gn:country_code":"FM",
    "gn:dem":-9999,
    "gn:feature_class":"P",
    "gn:feature_code":"PPL",
    "gn:name":"Bulwol - temp LL",
    "gn:population":0,
    "gn:timezone":"Pacific/Chuuk",
    "iso:country":"FM",
    "wof:name":"Bulwol - temp LL",
    "wof:placetype":"locality"
},
  "geometry": {"coordinates":[138.14715000000001,9.63443],"type":"Point"}
}