{
  "type": "Feature",
  "properties": {
    "gn:admin1_code":"03",
    "gn:admin2_code":"SA",
    "gn:asciiname":"Satowan",
    "gn:country_code":"FM",
    "gn:dem":24,
    "gn:feature_class":"P",
    "gn:feature_code":"PPLA2",
    "gn:name":"Satowan",
    "gn:population":0,
    "gn:timezone":"Pacific/Chuuk",
    "iso:country":"FM",
    "wof:name":"Satowan",
    "wof:placetype":"locality"
},
  "geometry": {"coordinates":[153.738,5.334],"type":"Point"}
}