{
  "type": "Feature",
  "properties": {
    "abrv:eng_x_preferred":[
        "SPOONFULL"
    ],
    "gn:country":"FM",
    "gn:fcode":"ATOL",
    "gn:pop":26,
    "iso:country":"FM",
    "name:ceb_x_preferred":[
        "Ngulu Atoll"
    ],
    "name:ces_x_preferred":[
        "Ngulu"
    ],
    "name:deu_x_preferred":[
        "Ngulu"
    ],
    "name:eng_x_preferred":[
        "Ngulu Atoll"
    ],
    "name:fas_x_preferred":[
        "\u0646\u06af\u0648\u0644\u0648"
    ],
    "name:fra_x_preferred":[
        "Ngulu"
    ],
    "name:ita_x_preferred":[
        "Ngulu"
    ],
    "name:jpn_x_preferred":[
        "\u30cc\u30b0\u30fc\u30eb\u74b0\u7901"
    ],
    "name:lit_x_preferred":[
        "Ngulu"
    ],
    "name:nld_x_preferred":[
        "Ngulu Atoll"
    ],
    "name:slv_x_preferred":[
        "Ngulu"
    ],
    "name:spa_x_preferred":[
        "Ngulu"
    ],
    "name:swe_x_preferred":[
        "Ngulu Atoll"
    ],
    "name:unk_x_variant":[
        "Angegul"
    ],
    "name:zho_x_preferred":[
        "\u6069\u53e4\u76e7\u74b0\u7901"
    ],
    "qs:name":"Ngulu Atoll",
    "qs:photos_9r":0,
    "qs:photos_sr":0,
    "qs:pop_sr":"1",
    "wd:wordcount":277,
    "wof:name":"Ngulu Atoll",
    "wof:placetype":"locality",
    "wof:population":26
},
  "geometry": {"coordinates":[137.482,8.45],"type":"Point"}
}