{
  "type": "Feature",
  "properties": {
    "abrv:eng_x_preferred":[
        "SPOONFULL"
    ],
    "gn:country":"FM",
    "gn:fcode":"ATOL",
    "gn:pop":26,
    "iso:country":"FM",
    "name:unk_x_variant":[
        "Angegul"
    ],
    "qs:name":"Ngulu Atoll",
    "qs:photos_9r":0,
    "qs:photos_sr":0,
    "qs:pop_sr":"1",
    "wd:wordcount":277,
    "wof:name":"Ngulu Atoll",
    "wof:placetype":"locality",
    "wof:population":26
},
  "geometry": {"coordinates":[137.482,8.45],"type":"Point"}
}