{
  "type": "Feature",
  "properties": {
    "gn:country":"FM",
    "gn:fcode":"PPL",
    "gn:pop":245,
    "iso:country":"FM",
    "qs:name":"Pisaras Village",
    "qs:photos_9r":0,
    "qs:photos_sr":0,
    "qs:pop_sr":"2",
    "wd:wordcount":40,
    "wof:name":"Pisaras Village",
    "wof:placetype":"locality",
    "wof:population":245
},
  "geometry": {"coordinates":[150.41541000000001,8.57169],"type":"Point"}
}