{
  "type": "Feature",
  "properties": {
    "gn:admin1_code":"03",
    "gn:admin2_code":"TL",
    "gn:asciiname":"Wichukuno - temp LL",
    "gn:cc2":"FM",
    "gn:country_code":"FM",
    "gn:dem":55,
    "gn:elevation":"6.0",
    "gn:feature_class":"P",
    "gn:feature_code":"PPL",
    "gn:name":"Wichukuno - temp LL",
    "gn:population":0,
    "gn:timezone":"Pacific/Chuuk",
    "iso:country":"FM",
    "name:und_x_variant":[
        "Wichuk"
    ],
    "wof:name":"Wichukuno - temp LL",
    "wof:placetype":"locality"
},
  "geometry": {"coordinates":[151.61146000000005,7.35163],"type":"Point"}
}