{
  "type": "Feature",
  "properties": {
    "abrv:eng_x_preferred":[
        "PRUDENTIAL"
    ],
    "gn:country":"FM",
    "gn:fcode":"ISL",
    "gn:population":523,
    "iso:country":"FM",
    "name:und_x_variant":[
        "Pis Island"
    ],
    "qs:name":"Piis Island",
    "qs:photos_9r":0,
    "qs:photos_sr":0,
    "qs:pop_sr":"2",
    "wof:name":"Piis Island",
    "wof:placetype":"locality",
    "wof:population":523
},
  "geometry": {"coordinates":[151.7636,7.678],"type":"Point"}
}