{
  "type": "Feature",
  "properties": {
    "gn:country":"FM",
    "gn:fcode":"ISL",
    "gn:population":681,
    "iso:country":"FM",
    "name:ceb_x_preferred":[
        "Fanapanges Island"
    ],
    "name:eng_x_preferred":[
        "Fala-Beguets"
    ],
    "name:fas_x_preferred":[
        "\u0641\u0627\u0644\u0627-\u0628\u06af\u0648\u0626\u062a\u0633"
    ],
    "name:fra_x_preferred":[
        "Fanapanges"
    ],
    "name:ita_x_preferred":[
        "Fanapanges"
    ],
    "name:mkd_x_preferred":[
        "\u0424\u0430\u043b\u0430-\u0411\u0435\u0433\u0443\u0435\u0446"
    ],
    "name:nld_x_preferred":[
        "Fala-Beguets"
    ],
    "name:pol_x_preferred":[
        "Fanapanges"
    ],
    "name:por_x_preferred":[
        "Fala-Beguets"
    ],
    "name:spa_x_preferred":[
        "Fanapanges"
    ],
    "name:swe_x_preferred":[
        "Fanapanges Island"
    ],
    "name:und_x_variant":[
        "Kayo To"
    ],
    "name:zho_x_preferred":[
        "\u6cd5\u62c9-\u8d1d\u76d6\u8328\u5c9b"
    ],
    "qs:name":"Fanapanges Island",
    "qs:photos_9r":0,
    "qs:photos_sr":0,
    "qs:pop_sr":"2",
    "wof:name":"Fanapanges Island",
    "wof:placetype":"locality",
    "wof:population":681
},
  "geometry": {"coordinates":[151.6678,7.353],"type":"Point"}
}