{
  "type": "Feature",
  "properties": {
    "gn:country":"FM",
    "gn:fcode":"ISL",
    "gn:pop":681,
    "iso:country":"FM",
    "name:dut_x_preferred":[
        "Fala-Beguets"
    ],
    "name:eng_x_preferred":[
        "Fala-Beguets"
    ],
    "name:fre_x_preferred":[
        "Fanapanges"
    ],
    "name:ita_x_preferred":[
        "Fanapanges"
    ],
    "name:mac_x_preferred":[
        "\u0424\u0430\u043b\u0430-\u0411\u0435\u0433\u0443\u0435\u0446"
    ],
    "name:pol_x_preferred":[
        "Fanapanges"
    ],
    "name:swe_x_preferred":[
        "Fanapanges Island"
    ],
    "name:unk_x_variant":[
        "Kayo To"
    ],
    "qs:name":"Fanapanges Island",
    "qs:photos_9r":0,
    "qs:photos_sr":0,
    "qs:pop_sr":"2",
    "wof:name":"Fanapanges Island",
    "wof:placetype":"locality",
    "wof:population":681
},
  "geometry": {"coordinates":[151.6678,7.353],"type":"Point"}
}